pianopy/__init__.py
pianopy/__main__.py
pianopy/colors.py
pianopy/midi.py
pianopy/notes.py
pianopy/piano.py
pianopy-0.0.2.dist-info/LICENSE
pianopy-0.0.2.dist-info/WHEEL
pianopy-0.0.2.dist-info/entry_points.txt
pianopy-0.0.2.dist-info/METADATA
pianopy-0.0.2.dist-info/RECORD
