Metadata-Version: 2.1
Name: pianopy
Version: 0.0.2
Summary: A python library/application to play, compose and interface with virtual and real pianos using MIDI.
Home-page: https://github.com/PeterPyPan/pianopy
License: MIT
Keywords: piano,music,game
Author: PeterPyPan
Author-email: PeterPyPanGitHub@gmail.com
Requires-Python: >=3.8,<4.0
Classifier: License :: OSI Approved :: MIT License
Classifier: Programming Language :: Python :: 3
Classifier: Programming Language :: Python :: 3.8
Classifier: Programming Language :: Python :: 3.9
Classifier: Programming Language :: Python :: 3.10
Classifier: Programming Language :: Python :: 3.11
Requires-Dist: mingus (>=0.6.1,<0.7.0)
Requires-Dist: numpy (>=1.24.1,<2.0.0)
Requires-Dist: pygame (>=2.1.2,<3.0.0)
Requires-Dist: python-rtmidi (>=1.4.9,<2.0.0)
Project-URL: Repository, https://github.com/python-poetry/poetry
